dbtype_checker/__init__.py
dbtype_checker/checker.py
dbtype_checker/cli.py
dbtype_checker/core.py
dbtype_checker/db.py
dbtype_checker/utils.py
dbtype_checker-0.1.12.dist-info/LICENSE
dbtype_checker-0.1.12.dist-info/METADATA
dbtype_checker-0.1.12.dist-info/WHEEL
dbtype_checker-0.1.12.dist-info/entry_points.txt
dbtype_checker-0.1.12.dist-info/top_level.txt
dbtype_checker-0.1.12.dist-info/RECORD
