Metadata-Version: 2.1
Name: dbtype_checker
Version: 0.1.12
Summary: Detect mismatched column types & correct them in your database using SQLAlchemy .
Author-email: Paras Seekhwal <Parasseekhwal@gmail.com>
License: MIT
Requires-Python: >=3.7
License-File: LICENSE
Requires-Dist: pandas
Requires-Dist: requests
Requires-Dist: sqlalchemy
Requires-Dist: typer
Requires-Dist: pymysql
Requires-Dist: pg8000
Requires-Dist: cx-Oracle
Requires-Dist: pyodbc
Requires-Dist: python-dotenv
